iointel/__init__.py
iointel/client/__init__.py
iointel/client/client.py
iointel/src/__init__.py
iointel/src/agents.py
iointel/src/chainables.py
iointel/src/memory.py
iointel/src/task.py
iointel/src/workflow.py
iointel/src/RL/README.md
iointel/src/RL/critic.py
iointel/src/RL/example_tools.py
iointel/src/RL/oracle.py
iointel/src/RL/task_manager.py
iointel/src/RL/training.py
iointel/src/RL/utils.py
iointel/src/RL/tests/tasks.json
iointel/src/RL/tests/testing.py
iointel/src/agent_methods/__init__.py
iointel/src/agent_methods/agents/__init__.py
iointel/src/agent_methods/agents/agents_factory.py
iointel/src/agent_methods/agents/tool_factory.py
iointel/src/agent_methods/data_models/__init__.py
iointel/src/agent_methods/data_models/datamodels.py
iointel/src/agent_methods/prompts/__init__.py
iointel/src/agent_methods/prompts/instructions.py
iointel/src/agent_methods/tools/__init__.py
iointel/src/agent_methods/tools/coinmarketcap.py
iointel/src/agent_methods/tools/duckduckgo.py
iointel/src/agent_methods/tools/firecrawl.py
iointel/src/agent_methods/tools/retrieval_engine.py
iointel/src/agent_methods/tools/searxng.py
iointel/src/agent_methods/tools/solscan.py
iointel/src/agent_methods/tools/tools.py
iointel/src/agent_methods/tools/utils.py
iointel/src/agent_methods/tools/wolfram.py
iointel/src/agent_methods/tools/agno/__init__.py
iointel/src/agent_methods/tools/agno/agentql.py
iointel/src/agent_methods/tools/agno/airflow.py
iointel/src/agent_methods/tools/agno/api.py
iointel/src/agent_methods/tools/agno/arxiv.py
iointel/src/agent_methods/tools/agno/aws_lambda.py
iointel/src/agent_methods/tools/agno/baidusearch.py
iointel/src/agent_methods/tools/agno/browserbase.py
iointel/src/agent_methods/tools/agno/calculator.py
iointel/src/agent_methods/tools/agno/cartesia.py
iointel/src/agent_methods/tools/agno/clickup.py
iointel/src/agent_methods/tools/agno/common.py
iointel/src/agent_methods/tools/agno/confluence.py
iointel/src/agent_methods/tools/agno/crawl4ai.py
iointel-1.7.2.dist-info/METADATA
iointel-1.7.2.dist-info/WHEEL
iointel-1.7.2.dist-info/licenses/LICENSE
iointel-1.7.2.dist-info/RECORD
