Metadata-Version: 2.4
Name: iointel
Version: 1.7.2
Summary: A framework to create agents, tasks, and workflows.
License-File: LICENSE
Keywords: AI,Agents,LLM,framework,tools
Classifier: Topic :: Software Development :: Libraries :: Python Modules
Requires-Python: >=3.10
Requires-Dist: agno[tools]==1.5.5
Requires-Dist: aiosqlite>=0.21.0
Requires-Dist: backoff==2.2.1
Requires-Dist: duckduckgo-search==8.0.2
Requires-Dist: firecrawl>=4.0.0
Requires-Dist: httpx
Requires-Dist: pgvector>=0.4.0
Requires-Dist: pydantic-ai==1.0.9
Requires-Dist: pydantic==2.11.9
Requires-Dist: python-dotenv>=1.0.1
Requires-Dist: python-multipart>=0.0.20
Requires-Dist: pyyaml>=6.0.2
Requires-Dist: rich>=13.9.4
Requires-Dist: sqlalchemy-utils>=0.41.2
Requires-Dist: sqlalchemy>=2.0.36
Provides-Extra: dev
Requires-Dist: pre-commit>=4.1.0; extra == 'dev'
Requires-Dist: pytest-asyncio>=1.1.0; extra == 'dev'
Requires-Dist: pytest-dotenv>=0.5.2; extra == 'dev'
Requires-Dist: pytest-rerunfailures<14,>=10; extra == 'dev'
Requires-Dist: pytest-retry>=1.7.0; extra == 'dev'
Requires-Dist: pytest-sugar<2.0,>=0.9; extra == 'dev'
Requires-Dist: pytest-timeout>=2.3.1; extra == 'dev'
Requires-Dist: pytest-xdist>=3.6.1; extra == 'dev'
Requires-Dist: pytest>=8.3.4; extra == 'dev'
Requires-Dist: yfinance==0.2.61; extra == 'dev'
Provides-Extra: ui
Requires-Dist: gradio>=5.32.1; extra == 'ui'
Requires-Dist: matplotlib>=3.10.3; extra == 'ui'
